README.md
setup.py
mailing/__init__.py
mailing/apps.py
mailing/conf.py
mailing/models.py
mailing/services.py
mailing/tasks.py
mailing/management/__init__.py
mailing/management/commands/__init__.py
mailing/management/commands/sendmail.py
mailing/migrations/0001_initial.py
mailing/migrations/0002_auto_20200722_1834.py
mailing/migrations/0003_email_email_from.py
mailing/migrations/0004_alter_email_id.py
mailing/migrations/__init__.py
portant_mailing.egg-info/PKG-INFO
portant_mailing.egg-info/SOURCES.txt
portant_mailing.egg-info/dependency_links.txt
portant_mailing.egg-info/not-zip-safe
portant_mailing.egg-info/requires.txt
portant_mailing.egg-info/top_level.txt
tests/__init__.py
tests/mailing_factories.py
tests/test_mailing.py
tests/test_settings.py