Metadata-Version: 2.1
Name: portant-mailing
Version: 1.0.4
Summary: a Django mailing app for Portant shop
Home-page: https://github.com/portant-shop/mailing
Author: Vedran Vojvoda
Author-email: vedran@pinkdroids.com
License: MIT
Platform: UNKNOWN
Classifier: Development Status :: 5 - Production/Stable
Classifier: Environment :: Web Environment
Classifier: Intended Audience :: Developers
Classifier: License :: OSI Approved :: BSD License
Classifier: Operating System :: OS Independent
Classifier: Programming Language :: Python
Classifier: Programming Language :: Python :: 3
Classifier: Framework :: Django
Provides-Extra: testing
